ngs_analysis/app.py
ngs_analysis/constants.py
ngs_analysis/interactive.py
ngs_analysis/sequence.py
ngs_analysis/timer.py
ngs_analysis-0.0.3.dist-info/LICENSE
ngs_analysis-0.0.3.dist-info/METADATA
ngs_analysis-0.0.3.dist-info/WHEEL
ngs_analysis-0.0.3.dist-info/entry_points.txt
ngs_analysis-0.0.3.dist-info/top_level.txt
ngs_analysis-0.0.3.dist-info/RECORD
