Metadata-Version: 2.1
Name: ngs-analysis
Version: 0.0.3
Summary: Analyze deep sequencing of complex libraries
Author: David Feldman
Project-URL: Homepage, https://github.com/feldman4/ngs-analysis
Project-URL: Bug Tracker, https://github.com/feldman4/ngs-analysis/issues
Keywords: NGS,library,variant,barcode
Classifier: Programming Language :: Python :: 3
Classifier: License :: OSI Approved :: MIT License
Classifier: Operating System :: OS Independent
Requires-Python: >=3.9
License-File: LICENSE
Requires-Dist: fire
Requires-Dist: glob2
Requires-Dist: ipykernel
Requires-Dist: natsort
Requires-Dist: pandas
Requires-Dist: pandera
Requires-Dist: parse
Requires-Dist: pyarrow
Requires-Dist: python-levenshtein
Requires-Dist: python-slugify
Requires-Dist: pyyaml
Requires-Dist: regex
Requires-Dist: tqdm
